sure_shot_static/__init__.py
sure_shot_static/intergalactic.py
sure_shot_static/shake_your_rump.py
sure_shot_static-1.2.2.dist-info/entry_points.txt
sure_shot_static-1.2.2.dist-info/WHEEL
sure_shot_static-1.2.2.dist-info/METADATA
sure_shot_static-1.2.2.dist-info/RECORD
