Metadata-Version: 2.1
Name: sure-shot-static
Version: 1.2.2
Summary: 
Author: doubleO8
Author-email: wb008@hdm-stuttgart.de
Requires-Python: >=3.6,<4.0
Classifier: Programming Language :: Python :: 3
Classifier: Programming Language :: Python :: 3.6
Classifier: Programming Language :: Python :: 3.7
Classifier: Programming Language :: Python :: 3.8
Classifier: Programming Language :: Python :: 3.9
Requires-Dist: Brotli (>=1.0.9,<2.0.0)
Requires-Dist: boto3 (>=1.17.21,<2.0.0)
Requires-Dist: python-magic (>=0.4.22,<0.5.0)
